camelipsum.py
setup.py
camelipsum.egg-info/PKG-INFO
camelipsum.egg-info/SOURCES.txt
camelipsum.egg-info/dependency_links.txt
camelipsum.egg-info/not-zip-safe
camelipsum.egg-info/requires.txt
camelipsum.egg-info/top_level.txt